risus/__init__.py
risus/risus.py
Risus-0.0.1.dist-info/LICENSE
Risus-0.0.1.dist-info/METADATA
Risus-0.0.1.dist-info/WHEEL
Risus-0.0.1.dist-info/top_level.txt
Risus-0.0.1.dist-info/RECORD
