Metadata-Version: 2.1
Name: Risus
Version: 0.0.1
Summary: Compute outcome probabilities for Risus: The Anything RPG
Author-email: "Preston M. Firestone" <firestone.preston@gmail.com>
License: GNU GENERAL PUBLIC LICENSE
License-File: LICENSE
Requires-Dist: numpy
Requires-Dist: pandas
Requires-Dist: icepool
